LICENSE.txt
evo_package_chat/__init__.py
evo_package_chat/automation/api.yaml
evo_package_chat/automation/entity.yaml
evo_package_chat/control/CChatApi.py
evo_package_chat/control/__init__.py
evo_package_chat/entity/EChatInput.py
evo_package_chat/entity/EChatMapMessage.py
evo_package_chat/entity/EChatMapModel.py
evo_package_chat/entity/EChatMapSession.py
evo_package_chat/entity/EChatMessage.py
evo_package_chat/entity/EChatModel.py
evo_package_chat/entity/EChatParameter.py
evo_package_chat/entity/EChatSession.py
evo_package_chat/entity/EnumChatRole.py
evo_package_chat/entity/__init__.py
evo_package_chat/utility/IChatProtocol.py
evo_package_chat/utility/UChatApi.py
evo_package_chat/utility/__init__.py
evo_package_chat-2024.10.22328.dist-info/LICENSE.txt
evo_package_chat-2024.10.22328.dist-info/METADATA
evo_package_chat-2024.10.22328.dist-info/WHEEL
evo_package_chat-2024.10.22328.dist-info/RECORD
